AUTHORS
MANIFEST.in
README.rst
setup.cfg
setup.py
Flask_Triangle_joeflack4.egg-info/PKG-INFO
Flask_Triangle_joeflack4.egg-info/SOURCES.txt
Flask_Triangle_joeflack4.egg-info/dependency_links.txt
Flask_Triangle_joeflack4.egg-info/not-zip-safe
Flask_Triangle_joeflack4.egg-info/requires.txt
Flask_Triangle_joeflack4.egg-info/top_level.txt
flask_triangle/__init__.py
flask_triangle/form.py
flask_triangle/jinja.py
flask_triangle/modifier.py
flask_triangle/schema.py
flask_triangle/triangle.py
flask_triangle/widget.py
flask_triangle/helpers/__init__.py
flask_triangle/helpers/html.py
flask_triangle/helpers/python3.py
flask_triangle/modifiers/__init__.py
flask_triangle/modifiers/base.py
flask_triangle/modifiers/limits.py
flask_triangle/modifiers/multiple.py
flask_triangle/modifiers/noschema.py
flask_triangle/modifiers/patterns.py
flask_triangle/modifiers/required.py
flask_triangle/modifiers/strict.py
flask_triangle/modifiers/typemod.py
flask_triangle/modifiers/types.py
flask_triangle/schema/__init__.py
flask_triangle/schema/base.py
flask_triangle/schema/containers.py
flask_triangle/schema/natural.py
flask_triangle/schema/tools.py
flask_triangle/widgets/__init__.py
flask_triangle/widgets/widget.py
flask_triangle/widgets/special/__init__.py
flask_triangle/widgets/special/label.py
flask_triangle/widgets/special/nowidget.py
flask_triangle/widgets/standard/__init__.py
flask_triangle/widgets/standard/select.py
flask_triangle/widgets/standard/text.py
flask_triangle/widgets/uibootstrap/__init__.py
flask_triangle/widgets/uibootstrap/datepicker.py
flask_triangle/widgets/uibootstrap/typeahead.py