Metadata-Version: 1.1
Name: Flask-Triangle-joeflack4
Version: 0.5.5.dev0
Summary: Integration of AngularJS and Flask, originally created by Morgan Delahaye-Prat (mdp@m-del.fr).
Home-page: http://flask-triangle.readthedocs.org/
Author: Joe Flack
Author-email: joeflack4@gmail.com
License: BSD
Download-URL: https://github.com/joeflack4/flask-triangle/tarball/v0.5.5
Keywords: flask,angular,jinja2,angular js,flask triangle
Platform: any
Classifier: Development Status :: 4 - Beta
Classifier: Intended Audience :: Developers
Classifier: License :: OSI Approved :: BSD License
Classifier: Operating System :: OS Independent
Classifier: Programming Language :: Python
Classifier: Programming Language :: Python :: 2.7
Classifier: Programming Language :: Python :: 3.3
Classifier: Programming Language :: Python :: 3.4
Classifier: Environment :: Web Environment
Classifier: Framework :: Flask
